{
    "date": "2026/01/16",
    "name": "長後市民センター前",
    "position": "-",
    "system": "長36",
    "destinations": [
        "長後駅西口"
    ],
    "weekday": [
        "6:37",
        "7:44",
        "9:54",
        "11:37",
        "16:59",
        "18:13",
        "18:57"
    ],
    "saturday": [
        "8:50",
        "14:44",
        "15:50",
        "16:41"
    ],
    "holiday": [
        "8:50",
        "15:24",
        "16:41"
    ],
    "url": "https://www.kanachu.co.jp/dia/diagram/timetable01_js/course:0000804115-19/node:00129813/kt:0/lname:/"
}
