{
    "date": "2025/11/16",
    "name": "山下団地入口",
    "position": "-",
    "system": "平28",
    "destinations": [
        "神明下",
        "平塚大橋",
        "上平塚",
        "平塚農商高校",
        "貴峯荘前",
        "中里(平塚市)",
        "柳町入口",
        "桧扇町",
        "大鳥公園前(平塚市)",
        "見附町",
        "明石町四丁目",
        "明石町(平塚市)",
        "明石町一丁目",
        "四ツ角(平塚市)",
        "平塚駅北口"
    ],
    "weekday": [
        "6:11",
        "6:31",
        "6:51",
        "7:11",
        "7:31",
        "7:51",
        "8:11",
        "8:41",
        "9:13",
        "9:43",
        "10:13",
        "10:43",
        "11:13",
        "11:43",
        "12:13",
        "12:43",
        "13:13",
        "13:43",
        "14:13",
        "14:43",
        "15:13",
        "15:43",
        "16:13",
        "16:43",
        "17:13",
        "17:43",
        "18:43",
        "19:43",
        "20:41",
        "21:41"
    ],
    "saturday": [
        "6:41",
        "7:41",
        "8:11",
        "8:41",
        "9:11",
        "9:41",
        "10:26",
        "11:06",
        "11:46",
        "12:26",
        "13:06",
        "13:46",
        "14:26",
        "15:06",
        "15:46",
        "16:26",
        "17:06",
        "17:46",
        "18:26",
        "19:06",
        "19:46",
        "20:56"
    ],
    "holiday": [
        "7:26",
        "8:11",
        "8:41",
        "9:11",
        "9:41",
        "10:26",
        "11:06",
        "11:46",
        "12:26",
        "13:06",
        "13:46",
        "14:26",
        "15:06",
        "15:46",
        "16:26",
        "17:06",
        "17:46",
        "18:26",
        "19:06",
        "19:46",
        "20:56"
    ],
    "url": "https://www.kanachu.co.jp/dia/diagram/timetable01_js/course:0000800018-9/node:00127574/kt:0/lname:/"
}
