{
    "date": "2024/04/01",
    "name": "三屋出口",
    "position": "-",
    "system": "秦12",
    "destinations": [
        "塚原橋(秦野市)",
        "古墳公園前",
        "上河原(秦野市)",
        "平和橋(秦野市)",
        "大倉入口",
        "関(秦野市)",
        "堀川",
        "堀西駐在所前",
        "中道(秦野市)",
        "西小学校前(秦野市)",
        "西中学校前(秦野市)",
        "柳町(秦野市)",
        "渋沢駅北口"
    ],
    "weekday": [
        "6:32",
        "8:19",
        "8:57",
        "9:49",
        "11:02",
        "15:02",
        "16:02",
        "18:52"
    ],
    "saturday": [
        "8:53",
        "9:53",
        "11:17",
        "14:06",
        "16:17",
        "17:21"
    ],
    "holiday": [
        "8:53",
        "9:53",
        "11:17",
        "14:06",
        "16:17",
        "17:21"
    ],
    "url": "https://www.kanachu.co.jp/dia/diagram/timetable01_js/course:0000802748-11/node:00127920/kt:0/lname:/"
}
