{
    "date": "2025/02/24",
    "name": "大運寺",
    "position": "-",
    "system": "戸50",
    "destinations": [
        "横浜医療センター前",
        "三叉路(横浜市戸塚区)",
        "横浜薬大南門",
        "俣野公園・横浜薬大前",
        "集会所前(横浜市戸塚区)",
        "ドリームハイツ"
    ],
    "weekday": [
        "6:36",
        "6:51",
        "7:06",
        "7:20",
        "7:29",
        "7:51",
        "7:54",
        "8:05",
        "8:09",
        "8:15",
        "8:19",
        "8:27",
        "8:36",
        "8:42",
        "9:38",
        "9:53",
        "10:03",
        "10:19",
        "10:28",
        "10:36",
        "10:53",
        "11:02",
        "11:19",
        "11:28",
        "11:36",
        "11:53",
        "12:02",
        "12:28",
        "13:02",
        "14:19",
        "14:28",
        "14:36",
        "14:53",
        "15:02",
        "15:19",
        "15:28",
        "15:36",
        "15:53",
        "16:02",
        "16:28",
        "16:36",
        "16:44",
        "16:54",
        "17:04",
        "17:11",
        "17:19",
        "17:26",
        "17:40",
        "17:54",
        "18:38",
        "18:43",
        "18:48",
        "18:54",
        "19:16",
        "19:26",
        "19:58",
        "20:06",
        "20:25",
        "20:39",
        "20:53",
        "21:06",
        "21:24",
        "21:33",
        "21:51",
        "22:09",
        "22:29",
        "22:49",
        "23:09"
    ],
    "saturday": [
        "6:15",
        "6:36",
        "6:51",
        "7:03",
        "7:11",
        "7:21",
        "7:31",
        "7:41",
        "7:51",
        "8:01",
        "8:11",
        "8:21",
        "8:31",
        "8:51",
        "9:01",
        "9:19",
        "9:26",
        "9:34",
        "9:49",
        "9:56",
        "10:04",
        "10:19",
        "10:26",
        "10:34",
        "10:49",
        "10:56",
        "11:04",
        "11:19",
        "11:26",
        "11:34",
        "11:49",
        "11:56",
        "12:04",
        "12:19",
        "12:26",
        "12:34",
        "12:49",
        "12:56",
        "13:04",
        "13:19",
        "13:26",
        "13:34",
        "13:49",
        "13:56",
        "14:04",
        "14:19",
        "14:26",
        "14:34",
        "14:49",
        "14:56",
        "15:04",
        "15:19",
        "15:26",
        "15:34",
        "15:49",
        "15:56",
        "16:04",
        "16:19",
        "16:26",
        "16:34",
        "16:49",
        "16:56",
        "17:04",
        "17:19",
        "17:26",
        "17:34",
        "17:41",
        "17:49",
        "17:56",
        "18:04",
        "18:11",
        "18:19",
        "18:26",
        "18:34",
        "18:41",
        "18:49",
        "18:56",
        "19:04",
        "19:11",
        "19:19",
        "19:26",
        "19:34",
        "19:41",
        "19:49",
        "19:56",
        "20:04",
        "20:21",
        "20:41",
        "21:01",
        "21:20",
        "21:40",
        "22:00",
        "22:22",
        "22:50"
    ],
    "holiday": [
        "6:15",
        "6:36",
        "6:51",
        "7:08",
        "7:23",
        "7:31",
        "7:41",
        "7:51",
        "8:01",
        "8:11",
        "8:21",
        "8:31",
        "8:51",
        "9:01",
        "9:19",
        "9:26",
        "9:34",
        "9:49",
        "9:56",
        "10:04",
        "10:19",
        "10:26",
        "10:34",
        "10:49",
        "10:56",
        "11:04",
        "11:19",
        "11:26",
        "11:34",
        "11:49",
        "11:56",
        "12:04",
        "12:19",
        "12:26",
        "12:34",
        "12:49",
        "12:56",
        "13:04",
        "13:19",
        "13:26",
        "13:34",
        "13:49",
        "13:56",
        "14:04",
        "14:19",
        "14:26",
        "14:34",
        "14:49",
        "14:56",
        "15:04",
        "15:19",
        "15:26",
        "15:34",
        "15:49",
        "15:56",
        "16:04",
        "16:19",
        "16:26",
        "16:34",
        "16:49",
        "16:56",
        "17:04",
        "17:19",
        "17:26",
        "17:34",
        "17:41",
        "17:49",
        "17:56",
        "18:04",
        "18:11",
        "18:19",
        "18:26",
        "18:34",
        "18:41",
        "18:49",
        "18:56",
        "19:04",
        "19:11",
        "19:19",
        "19:26",
        "19:34",
        "19:41",
        "19:49",
        "19:56",
        "20:04",
        "20:23",
        "20:47",
        "21:10",
        "21:34",
        "21:58",
        "22:22",
        "22:50"
    ],
    "url": "https://www.kanachu.co.jp/dia/diagram/timetable01_js/course:0000800862-10/node:00126817/kt:0/lname:/"
}
