{
    "date": "2025/04/01",
    "name": "上横町",
    "position": "",
    "system": "町15",
    "destinations": [
        "境川団地",
        "境川団地中央",
        "境川団地入口",
        "木曽都営入口",
        "桧台入口",
        "森野六丁目",
        "森野五丁目",
        "妙延寺(町田市)",
        "町田市役所市民ホール前",
        "町田バスセンター"
    ],
    "weekday": [
        "7:16",
        "20:54",
        "21:24"
    ],
    "saturday": [
        "6:26",
        "7:17",
        "7:41",
        "8:13",
        "8:43",
        "21:34"
    ],
    "holiday": [
        "6:32",
        "7:17",
        "7:47",
        "8:17",
        "8:47",
        "21:34"
    ],
    "url": "https://www.kanachu.co.jp/dia/diagram/timetable01_js/course:0000803207-8/node:00129385/kt:0/lname:/"
}
