{
    "date": "2025/08/04",
    "name": "相模原協同病院",
    "position": "-",
    "system": "相32",
    "destinations": [
        "峡の原車庫",
        "峡の原",
        "金属工業団地(相模原市緑区)",
        "緑ヶ丘(相模原市緑区)",
        "橋本十字路",
        "大山団地入口",
        "大河原(相模原市中央区)",
        "清新小学校前",
        "さがみ夢大通り",
        "相模原駅南口"
    ],
    "weekday": [
        "13:08",
        "13:48",
        "14:23",
        "15:03",
        "15:48",
        "16:23",
        "17:13",
        "17:43",
        "18:13",
        "18:38"
    ],
    "saturday": [
        "12:43",
        "13:13",
        "13:43",
        "14:13",
        "15:03",
        "15:33",
        "16:33",
        "17:13",
        "17:53"
    ],
    "holiday": [
        "17:13",
        "17:43"
    ],
    "url": "https://www.kanachu.co.jp/dia/diagram/timetable01_js/course:0000803002-1/node:00130514/kt:0/lname:/"
}
