{
    "date": "2024/12/16",
    "name": "河内富士見",
    "position": "-",
    "system": "平73",
    "destinations": [
        "纒公民館前",
        "川井(平塚市)",
        "纒入口",
        "南原土手",
        "南原(平塚市)",
        "向原(平塚市)",
        "江南高校前",
        "追分(平塚市)",
        "立野町(平塚市)",
        "横浜ゴム前",
        "市役所前(ゴム前/平塚市)",
        "四ツ角(平塚市)",
        "平塚駅北口"
    ],
    "weekday": [
        "6:01",
        "6:29",
        "7:10",
        "7:40",
        "8:16",
        "8:56",
        "9:23",
        "10:24",
        "11:15",
        "12:06",
        "13:08",
        "14:07",
        "15:07",
        "16:12",
        "17:16",
        "18:16",
        "18:52",
        "19:42",
        "20:38",
        "21:30"
    ],
    "saturday": [
        "6:19",
        "7:10",
        "7:58",
        "8:55",
        "10:00",
        "11:08",
        "12:08",
        "13:08",
        "14:08",
        "15:08",
        "16:09",
        "17:20",
        "18:01",
        "18:46",
        "19:47",
        "20:53",
        "21:29"
    ],
    "holiday": [
        "6:19",
        "7:10",
        "7:58",
        "8:55",
        "10:00",
        "11:08",
        "12:08",
        "13:08",
        "14:08",
        "15:08",
        "16:09",
        "17:20",
        "18:01",
        "18:46",
        "19:47",
        "20:53",
        "21:29"
    ],
    "url": "https://www.kanachu.co.jp/dia/diagram/timetable01_js/course:0000803657-18/node:00127744/kt:0/lname:/"
}
