{
    "date": "2025/08/04",
    "name": "森の上",
    "position": "-",
    "system": "橋28",
    "destinations": [
        "東原宿",
        "城山相原界",
        "本郷(相模原市緑区)",
        "砂(相模原市緑区)",
        "町屋本町",
        "広田小学校前",
        "かたくりの里",
        "若葉台七丁目",
        "新若葉台",
        "若葉台住宅"
    ],
    "weekday": [
        "15:56",
        "16:49",
        "17:54",
        "19:04",
        "19:57"
    ],
    "saturday": [
        "17:52",
        "18:27",
        "19:15"
    ],
    "holiday": [
        "17:52",
        "18:27",
        "19:15"
    ],
    "url": "https://www.kanachu.co.jp/dia/diagram/timetable01_js/course:0000803133-9/node:00128963/kt:0/lname:/"
}
