{
    "date": "2025/11/16",
    "name": "小野橋(厚木市)",
    "position": "-",
    "system": "愛15",
    "destinations": [
        "榎田",
        "若宮橋(厚木市)",
        "森の里一丁目",
        "森の里二丁目",
        "森の里小学校前",
        "森の里三丁目",
        "森の里中学校前",
        "北センター(厚木市)",
        "森の里五丁目",
        "森の里"
    ],
    "weekday": [
        "7:28",
        "7:55",
        "8:32",
        "9:36",
        "10:57",
        "12:17",
        "13:30",
        "14:52",
        "16:22",
        "17:37",
        "18:31",
        "19:32",
        "20:37",
        "21:37"
    ],
    "saturday": [
        "6:52",
        "8:13",
        "9:33",
        "10:53",
        "12:13",
        "13:33",
        "14:53",
        "16:13",
        "17:33",
        "18:53",
        "20:12",
        "21:32"
    ],
    "holiday": [
        "6:52",
        "8:13",
        "9:33",
        "10:53",
        "12:13",
        "13:33",
        "14:53",
        "16:13",
        "17:33",
        "18:53",
        "20:12",
        "21:32"
    ],
    "url": "https://www.kanachu.co.jp/dia/diagram/timetable01_js/course:0000800386-13/node:00128450/kt:0/lname:/"
}
