{
    "date": "2024/03/16",
    "name": "小山内裏公園南",
    "position": "-",
    "system": "橋76",
    "destinations": [
        "まちだテクノパーク前",
        "小山上沼公園",
        "多摩境通り北",
        "神奈中多摩車庫"
    ],
    "weekday": [
        "6:50",
        "7:13",
        "7:27",
        "7:45",
        "7:57",
        "8:07",
        "8:23",
        "8:37",
        "9:03",
        "9:14",
        "9:26",
        "9:42",
        "9:57",
        "10:14",
        "10:45",
        "10:57",
        "11:10",
        "11:22",
        "11:42",
        "12:07",
        "12:19",
        "12:44",
        "13:10",
        "13:37",
        "14:02",
        "14:22",
        "14:32",
        "14:52",
        "15:12",
        "15:27",
        "15:52",
        "16:16",
        "16:32",
        "16:54",
        "17:16",
        "17:26",
        "17:36",
        "17:52",
        "18:06",
        "18:20",
        "18:30",
        "18:40",
        "18:50",
        "19:02",
        "19:19",
        "19:39",
        "19:57",
        "20:17",
        "20:35",
        "20:55",
        "21:25",
        "21:55",
        "22:20",
        "23:01"
    ],
    "saturday": [
        "8:12",
        "8:37",
        "9:00",
        "9:15",
        "9:37",
        "9:55",
        "10:14",
        "10:42",
        "11:14",
        "11:50",
        "12:14",
        "12:42",
        "13:14",
        "13:44",
        "14:14",
        "14:42",
        "15:14",
        "15:37",
        "15:54",
        "16:24",
        "16:54",
        "17:14",
        "17:32",
        "17:54",
        "18:17",
        "18:34",
        "18:57",
        "19:15",
        "19:30",
        "19:57",
        "20:27",
        "20:57",
        "21:27",
        "21:57",
        "22:20"
    ],
    "holiday": [
        "8:18",
        "8:50",
        "9:20",
        "9:40",
        "10:14",
        "10:42",
        "11:14",
        "11:42",
        "12:14",
        "12:42",
        "13:14",
        "13:44",
        "14:14",
        "14:42",
        "15:14",
        "15:42",
        "16:14",
        "16:42",
        "17:14",
        "17:42",
        "18:14",
        "18:42",
        "19:12",
        "19:40",
        "20:12",
        "20:50",
        "21:50",
        "22:20"
    ],
    "url": "https://www.kanachu.co.jp/dia/diagram/timetable01_js/course:0000802977-11/node:00130119/kt:0/lname:/"
}
