{
    "date": "2025/04/01",
    "name": "森野三丁目",
    "position": "-",
    "system": "町31",
    "destinations": [
        "市民病院前(町田市)",
        "浄水場前(町田市)",
        "滝の沢(町田市)",
        "木曽住宅",
        "三家(町田市)",
        "木曽(町田市)",
        "忠生公園入口",
        "上宿(町田市)",
        "下根岸(町田市)",
        "根岸(根岸町/町田市)",
        "馬駈",
        "図師大橋",
        "図師",
        "松下谷戸",
        "結道",
        "日大三高東",
        "扇橋(町田市)",
        "多摩丘陵病院",
        "多摩丘陵リハビリテーション病院"
    ],
    "weekday": [
        "7:34",
        "8:35",
        "9:13",
        "10:39",
        "11:39",
        "13:03",
        "14:03",
        "14:42",
        "15:25",
        "16:20",
        "17:45",
        "18:15",
        "19:50"
    ],
    "saturday": [
        "8:14",
        "9:57",
        "11:40",
        "13:20",
        "15:10",
        "17:10"
    ],
    "holiday": [
        "8:12",
        "9:55",
        "11:45",
        "13:15",
        "15:10",
        "17:10"
    ],
    "url": "https://www.kanachu.co.jp/dia/diagram/timetable01_js/course:0000803323-4/node:00129358/kt:0/lname:/"
}
