{
    "date": "2025/04/19",
    "name": "東橋本一丁目",
    "position": "-",
    "system": "橋55",
    "destinations": [
        "宮下一丁目〔旧:協栄産業前〕",
        "三菱電機前",
        "日本酸素前",
        "向陽小学校前",
        "氷川神社前(相模原市中央区)",
        "清新本町",
        "相模原駅前郵便局",
        "相模原駅南口"
    ],
    "weekday": [
        "6:54",
        "7:24",
        "7:54",
        "8:19",
        "8:44",
        "9:34",
        "10:24",
        "11:14",
        "12:04",
        "12:54",
        "13:44",
        "14:34",
        "15:24",
        "16:14",
        "17:04",
        "17:54",
        "18:19",
        "19:09",
        "19:59"
    ],
    "saturday": [
        "7:19",
        "8:19",
        "9:19",
        "10:19",
        "11:19",
        "12:19",
        "13:19",
        "14:19",
        "15:19",
        "16:19",
        "17:19",
        "18:19"
    ],
    "holiday": [
        "7:19",
        "8:19",
        "9:19",
        "10:19",
        "11:19",
        "12:19",
        "13:19",
        "14:19",
        "15:19",
        "16:19",
        "17:19",
        "18:19"
    ],
    "url": "https://www.kanachu.co.jp/dia/diagram/timetable01_js/course:0000802357-5/node:00129192/kt:0/lname:/"
}
