{
    "date": "2026/01/16",
    "name": "鶴川市民センター入口",
    "position": "-",
    "system": "鶴66",
    "destinations": [
        "大蔵(鶴川郵便局前/町田市)",
        "春日台",
        "山王ガーデン入口",
        "山王ガーデン",
        "綾部入口",
        "袋橋",
        "田中入口",
        "野津田車庫"
    ],
    "weekday": [
        "7:30",
        "8:36",
        "9:30",
        "10:30",
        "11:30",
        "12:31",
        "13:30",
        "14:30",
        "15:30",
        "16:30",
        "17:31",
        "18:36",
        "19:36",
        "20:30"
    ],
    "saturday": [
        "8:30",
        "9:30",
        "10:30",
        "11:30",
        "12:37",
        "13:30",
        "14:30",
        "15:30",
        "16:30",
        "17:37",
        "18:34",
        "19:36",
        "20:19"
    ],
    "holiday": [
        "9:30",
        "10:30",
        "11:30",
        "12:37",
        "13:30",
        "14:30",
        "15:30",
        "16:30",
        "17:37",
        "18:34",
        "19:36"
    ],
    "url": "https://www.kanachu.co.jp/dia/diagram/timetable01_js/course:0000804196-5/node:00129436/kt:0/lname:/"
}
