{
    "date": "2025/11/16",
    "name": "八坂神社(中郡大磯町)",
    "position": "-",
    "system": "磯13",
    "destinations": [
        "白岩大門",
        "統監道",
        "大磯小学校前",
        "大磯駅"
    ],
    "weekday": [
        "7:31",
        "8:56",
        "9:39",
        "10:51",
        "11:51",
        "12:51",
        "13:51",
        "14:51",
        "15:51",
        "16:51",
        "17:59",
        "18:59",
        "19:59",
        "20:34",
        "21:24"
    ],
    "saturday": [
        "7:54",
        "8:34",
        "9:34",
        "10:34",
        "11:34",
        "12:34",
        "13:34",
        "14:34",
        "15:34",
        "16:34",
        "17:34",
        "18:34",
        "19:34"
    ],
    "holiday": [
        "7:54",
        "8:34",
        "9:34",
        "10:34",
        "11:34",
        "12:34",
        "13:34",
        "14:34",
        "15:34",
        "16:34",
        "17:34",
        "18:34",
        "19:34"
    ],
    "url": "https://www.kanachu.co.jp/dia/diagram/timetable01_js/course:0000801496-9/node:00127480/kt:0/lname:/"
}
