{
    "date": "2024/09/09",
    "name": "常盤園下",
    "position": "-",
    "system": "",
    "destinations": [
        "峰岡町",
        "峯小学校前",
        "宮田町(横浜市保土ケ谷区)",
        "洪福寺",
        "浅間町車庫前",
        "浅岡橋",
        "浅間下(横浜市西区)",
        "楠町",
        "鶴屋町三丁目",
        "横浜駅西口"
    ],
    "weekday": [
        "6:39",
        "7:02",
        "8:07",
        "9:07",
        "10:06",
        "11:13",
        "12:13",
        "13:13",
        "14:13",
        "15:13",
        "16:13",
        "17:13",
        "18:14",
        "19:14",
        "20:13",
        "21:20",
        "22:36"
    ],
    "saturday": [
        "6:16",
        "6:52",
        "7:50",
        "8:29",
        "9:06",
        "10:02",
        "11:02",
        "12:02",
        "13:02",
        "14:02",
        "15:02",
        "16:02",
        "17:02",
        "18:02",
        "19:02",
        "20:02",
        "20:37"
    ],
    "holiday": [
        "6:36",
        "7:33",
        "8:22",
        "8:55",
        "10:01",
        "11:01",
        "12:01",
        "13:01",
        "14:01",
        "15:01",
        "16:03",
        "17:02",
        "18:02",
        "19:02",
        "20:05",
        "20:35"
    ],
    "url": "https://www.kanachu.co.jp/dia/diagram/timetable01_js/course:0000802206-35/node:00102799/kt:0/lname:/"
}
