{
    "date": "2025/05/11",
    "name": "越戸橋(横浜市港南区)",
    "position": "-",
    "system": "船20",
    "destinations": [
        "最戸橋",
        "上大岡駅",
        "関の下",
        "笹下港南中央通り",
        "港南区総合庁舎前",
        "吉原(横浜市港南区)",
        "新吉原橋",
        "日野公園墓地入口",
        "日野中央公園入口",
        "日野小学校前(横浜市港南区)",
        "日野(横浜市港南区)",
        "清水橋(横浜市港南区)",
        "金井(横浜市港南区)",
        "藤ヶ沢",
        "港南車庫入口",
        "原(横浜市港南区)",
        "七曲",
        "鍛冶ヶ谷",
        "本郷石橋",
        "天神橋(横浜市栄区)",
        "栄警察署前",
        "公田",
        "鎌倉女子大前",
        "平島(鎌倉市)",
        "笠間十字路",
        "笠間町",
        "岩井口",
        "大船駅(横浜市栄区)"
    ],
    "weekday": [
        "7:47",
        "8:09",
        "8:38",
        "8:49",
        "9:04",
        "9:14",
        "9:24",
        "9:40",
        "9:50",
        "10:10",
        "10:32",
        "10:56",
        "11:20",
        "11:44",
        "12:08",
        "12:32",
        "12:56",
        "13:20",
        "13:44",
        "14:11",
        "14:32",
        "14:56",
        "15:20",
        "15:44",
        "16:08",
        "16:32",
        "16:56",
        "17:20",
        "17:44",
        "18:08",
        "18:32",
        "18:56",
        "19:21",
        "19:48",
        "20:06",
        "20:33",
        "20:54"
    ],
    "saturday": [
        "7:48",
        "8:20",
        "8:44",
        "9:05",
        "9:25",
        "9:40",
        "9:58",
        "10:21",
        "10:37",
        "10:50",
        "11:08",
        "11:28",
        "11:48",
        "12:09",
        "12:30",
        "12:50",
        "13:11",
        "13:35",
        "14:03",
        "14:34",
        "15:04",
        "15:35",
        "16:05",
        "16:35",
        "17:05",
        "17:35",
        "18:05",
        "18:33",
        "19:15",
        "19:33",
        "19:56",
        "20:29"
    ],
    "holiday": [
        "7:48",
        "8:20",
        "8:44",
        "9:05",
        "9:25",
        "9:40",
        "9:58",
        "10:21",
        "10:37",
        "10:50",
        "11:08",
        "11:28",
        "11:48",
        "12:09",
        "12:30",
        "12:50",
        "13:11",
        "13:35",
        "14:03",
        "14:34",
        "15:04",
        "15:35",
        "16:05",
        "16:35",
        "17:05",
        "17:35",
        "18:05",
        "18:33",
        "19:15",
        "19:33",
        "19:56",
        "20:29"
    ],
    "url": "https://www.kanachu.co.jp/dia/diagram/timetable01_js/course:0000803428-20/node:00102507/kt:0/lname:/"
}
