{
    "date": "2025/03/15",
    "name": "松が丘二丁目(茅ケ崎市)",
    "position": "-",
    "system": "辻10",
    "destinations": [
        "平和町",
        "浜須賀入口",
        "平和学園前(茅ケ崎市)",
        "富士見町(茅ケ崎市)",
        "東浜須賀",
        "茅ヶ崎学園入口",
        "のぞみ学園前",
        "辻堂団地",
        "高砂(藤沢市)",
        "久根下公園前",
        "辻堂駅南口"
    ],
    "weekday": [],
    "saturday": [
        "6:41",
        "7:41",
        "8:41",
        "9:41",
        "10:41",
        "11:41",
        "12:41",
        "13:41",
        "14:41",
        "15:41",
        "16:41",
        "17:41",
        "18:41",
        "19:41"
    ],
    "holiday": [
        "6:41",
        "7:41",
        "8:41",
        "9:41",
        "10:41",
        "11:41",
        "12:41",
        "13:41",
        "14:41",
        "15:41",
        "16:41",
        "17:41",
        "18:41",
        "19:41"
    ],
    "url": "https://www.kanachu.co.jp/dia/diagram/timetable01_js/course:0000803219-7/node:00127225/kt:0/lname:/"
}
