{
    "date": "2026/01/16",
    "name": "中田(横浜市保土ケ谷区)",
    "position": "-",
    "system": "01",
    "destinations": [
        "上菅田町",
        "笹山(横浜市保土ケ谷区)",
        "辻山",
        "地蔵前(横浜市緑区)",
        "鴨居町",
        "中村通",
        "鴨居橋",
        "白山一丁目(横浜市緑区)",
        "緑車庫前",
        "白山ハイテクパーク",
        "石神(横浜市緑区)",
        "上山町(横浜市緑区)",
        "中山小学校南",
        "中山町",
        "西村橋",
        "中山駅"
    ],
    "weekday": [
        "7:48",
        "8:05",
        "8:25",
        "9:19",
        "10:48",
        "12:02",
        "13:27",
        "15:01",
        "16:02",
        "17:16",
        "18:28",
        "19:27",
        "20:22",
        "20:56"
    ],
    "saturday": [
        "7:39",
        "8:26",
        "9:18",
        "10:41",
        "12:03",
        "13:16",
        "14:11",
        "15:11",
        "16:11",
        "17:14",
        "18:14",
        "19:10",
        "20:07"
    ],
    "holiday": [
        "7:39",
        "8:24",
        "9:14",
        "10:37",
        "11:59",
        "13:11",
        "14:11",
        "15:11",
        "16:11",
        "17:12",
        "18:09",
        "19:08",
        "20:07"
    ],
    "url": "https://www.kanachu.co.jp/dia/diagram/timetable01_js/course:0000804253-29/node:00102825/kt:0/lname:/"
}
