{
    "date": "2024/09/09",
    "name": "菅田町入口",
    "position": "-",
    "system": "",
    "destinations": [
        "八反橋",
        "羽沢下町",
        "羽沢町",
        "東泉寺前",
        "羽沢団地前",
        "三枚町",
        "生花市場前",
        "羽沢横浜国大駅前",
        "高山(横浜市神奈川区)",
        "羽沢南",
        "池の谷戸(横浜市保土ケ谷区)",
        "川島住宅",
        "杉山神社前(横浜市保土ケ谷区)",
        "上星川",
        "保土ヶ谷中学校前",
        "和田町(横浜市保土ケ谷区)",
        "常盤園下",
        "峰岡町",
        "峯小学校前",
        "宮田町(横浜市保土ケ谷区)",
        "洪福寺",
        "天王町(横浜市保土ケ谷区)",
        "天王町駅前",
        "大門通",
        "帷子町会館前",
        "保土ヶ谷駅西口"
    ],
    "weekday": [
        "6:49",
        "7:50",
        "8:50",
        "9:50",
        "10:53",
        "11:51",
        "12:50",
        "13:50",
        "14:50",
        "15:50",
        "16:50",
        "17:50",
        "18:50",
        "19:50"
    ],
    "saturday": [
        "6:50",
        "7:52",
        "8:50",
        "9:51",
        "10:54",
        "11:53",
        "12:53",
        "13:53",
        "14:53",
        "15:53",
        "16:54",
        "17:57",
        "18:57",
        "19:53"
    ],
    "holiday": [
        "6:52",
        "7:52",
        "8:49",
        "9:50",
        "10:53",
        "11:52",
        "12:52",
        "13:52",
        "14:52",
        "15:53",
        "16:53",
        "17:56",
        "18:56",
        "19:53"
    ],
    "url": "https://www.kanachu.co.jp/dia/diagram/timetable01_js/course:0000802228-4/node:00102657/kt:0/lname:/"
}
