{
    "date": "2025/10/20",
    "name": "中村(町田市成瀬)",
    "position": "-",
    "system": "成03",
    "destinations": [
        "成瀬高校入口",
        "南成瀬",
        "成瀬駅"
    ],
    "weekday": [
        "6:19",
        "7:11",
        "7:54",
        "8:23",
        "8:41",
        "9:46",
        "10:46",
        "11:46",
        "12:46",
        "13:46",
        "14:46",
        "15:46",
        "16:46",
        "17:46",
        "18:11",
        "19:06",
        "20:11"
    ],
    "saturday": [
        "7:46",
        "8:46",
        "9:46",
        "10:46",
        "11:46",
        "12:46",
        "13:46",
        "14:46",
        "15:46",
        "16:46",
        "17:46",
        "18:46",
        "19:46"
    ],
    "holiday": [
        "7:41",
        "8:46",
        "9:46",
        "10:46",
        "11:46",
        "12:46",
        "13:46",
        "14:46",
        "15:46",
        "16:46",
        "17:46",
        "18:46",
        "19:46"
    ],
    "url": "https://www.kanachu.co.jp/dia/diagram/timetable01_js/course:0000801139-11/node:00129560/kt:0/lname:/"
}
