{
    "date": "2025/03/15",
    "name": "ひばりが丘(茅ケ崎市)",
    "position": "-",
    "system": "辻12",
    "destinations": [
        "美住町",
        "松浪小学校前",
        "保育園前(茅ヶ崎市)",
        "浜竹",
        "辻堂駅西口",
        "辻堂駅南口"
    ],
    "weekday": [
        "5:56",
        "6:15",
        "6:33",
        "6:45",
        "6:57",
        "7:09",
        "7:24",
        "7:39",
        "7:54",
        "8:16",
        "8:36",
        "9:04",
        "9:34",
        "10:04",
        "10:34",
        "11:04",
        "11:34",
        "12:04",
        "12:34",
        "13:04",
        "13:34",
        "14:04",
        "14:34",
        "15:04",
        "15:34",
        "16:06",
        "16:34",
        "17:06",
        "17:34",
        "17:54",
        "18:14",
        "18:34",
        "18:54",
        "19:14",
        "19:34",
        "20:04",
        "20:34",
        "21:04",
        "21:34",
        "22:09"
    ],
    "saturday": [
        "6:24",
        "7:04",
        "7:34",
        "8:04",
        "8:34",
        "9:04",
        "9:34",
        "10:04",
        "10:34",
        "11:04",
        "11:34",
        "12:04",
        "12:34",
        "13:04",
        "13:34",
        "14:04",
        "14:34",
        "15:04",
        "15:34",
        "16:04",
        "16:34",
        "17:04",
        "17:34",
        "18:04",
        "18:34",
        "19:04",
        "19:34",
        "20:04",
        "20:49",
        "21:49"
    ],
    "holiday": [
        "6:24",
        "7:04",
        "7:34",
        "8:04",
        "8:34",
        "9:04",
        "9:34",
        "10:04",
        "10:34",
        "11:04",
        "11:34",
        "12:04",
        "12:34",
        "13:04",
        "13:34",
        "14:04",
        "14:34",
        "15:04",
        "15:34",
        "16:04",
        "16:34",
        "17:04",
        "17:34",
        "18:04",
        "18:34",
        "19:04",
        "19:34",
        "20:04",
        "20:49",
        "21:49"
    ],
    "url": "https://www.kanachu.co.jp/dia/diagram/timetable01_js/course:0000801834-11/node:00127237/kt:0/lname:/"
}
